__init__.py
sdqc_check/__init__.py
sdqc_check/utils.py
sdqc_check/causality/__init__.py
sdqc_check/causality/causal_analysis.py
sdqc_check/classification/__init__.py
sdqc_check/classification/classification_model.py
sdqc_check/explainability/__init__.py
sdqc_check/explainability/base.py
sdqc_check/explainability/model_based.py
sdqc_check/explainability/pfi.py
sdqc_check/explainability/shap.py
sdqc_check/statistical_test/__init__.py
sdqc_check/statistical_test/base_statistical_test.py
sdqc_check/statistical_test/categorical_test.py
sdqc_check/statistical_test/correlation.py
sdqc_check/statistical_test/numerical_test.py
sdqc_check/statistical_test/utils.py
sdqc_data/__init__.py
sdqc_data/read_data.py
sdqc_integration/__init__.py
sdqc_integration/sequential.py
sdqc_synthesize/__init__.py
sdqc_synthesize/base_synthesizer.py
sdqc_synthesize/sdv_synthesizer.py
sdqc_synthesize/ydata_synthesizer.py
sdqcpy-1.0.1.dist-info/LICENSE
sdqcpy-1.0.1.dist-info/METADATA
sdqcpy-1.0.1.dist-info/WHEEL
sdqcpy-1.0.1.dist-info/top_level.txt
sdqcpy-1.0.1.dist-info/RECORD
