Metadata-Version: 2.1
Name: sdqcpy
Version: 1.0.1
Summary: SDQCPy is a comprehensive Python package designed for synthetic data management, quality control, and validation.
Author-email: T0217 <tianyanggong17@outlook.com>
License: Apache-2.0
Project-URL: Homepage, https://github.com/T0217/sdqcpy
Project-URL: Bug Tracker, https://github.com/T0217/sdqcpy/issues
Keywords: synthetic data,data quality,data validation,data management
Classifier: Development Status :: 5 - Production/Stable
Classifier: Intended Audience :: Developers
Classifier: Intended Audience :: Science/Research
Classifier: License :: OSI Approved :: Apache Software License
Classifier: Natural Language :: English
Classifier: Operating System :: Microsoft :: Windows
Classifier: Operating System :: Unix
Classifier: Programming Language :: Python :: 3
Classifier: Programming Language :: Python :: 3.9
Classifier: Programming Language :: Python :: 3.10
Classifier: Programming Language :: Python :: 3.11
Classifier: Topic :: Software Development :: Libraries :: Python Modules
Classifier: Topic :: Scientific/Engineering :: Artificial Intelligence
Classifier: Topic :: Scientific/Engineering :: Information Analysis
Classifier: Topic :: Software Development :: Quality Assurance
Requires-Python: <3.12,>=3.9
License-File: LICENSE
Requires-Dist: pandas>=1.3.0
Requires-Dist: numpy>=1.20.0
Requires-Dist: scikit-learn>=1.0.0
Requires-Dist: scipy>=1.7.0
Requires-Dist: matplotlib>=3.4.0
Requires-Dist: seaborn>=0.11.0
Requires-Dist: tqdm>=4.60.0
Requires-Dist: jinja2>=3.0.0
Requires-Dist: gcastle>=1.0.0
Requires-Dist: shap>=0.41.0
Requires-Dist: lime>=0.2.0
Requires-Dist: xgboost>=1.4.0
Requires-Dist: lightgbm>=3.2.0
Requires-Dist: ydata-synthetic<2.0.0,>=1.0.0
Requires-Dist: sdv<1.17.0,>=0.17.0
Provides-Extra: test
Requires-Dist: pytest>=6.2.0; extra == "test"
Requires-Dist: flake8>=4.0.0; extra == "test"
Requires-Dist: autopep8>=1.5.0; extra == "test"
